{"id":"00185","locations":[{"status":"<div class=\"status pause\" title=\"Приостановлен\"></div>","address":"Омская обл, Саргатский р-н, рп Саргатское, ул 50 лет Победы, д. 4","capacity":"1","type":["M1","N1"],"coords":["55.599143","73.488811"]}],"company":[{"name":"Статус","value":"Аттестат приостановлен"},{"name":"Директор","value":"Нарсия Данил Григорьевич"},{"name":"Полное наименование","value":"ИП Нарсия Д. Г."},{"name":"ОГРН","value":"304553231600012"},{"name":"Орг. форма","value":"Индивидуальный предприниматель"},{"name":"Адрес","value":"646400, Омская область, Саргатский р-н., рп Саргатское, Саргатское рп."}],"contacts":[{"name":"Телефон","value":"8 (908) 102-3200"},{"name":"E-mail","value":"<a href=\"mailto:stoptosargatka@mail.ru\">stoptosargatka@mail.ru</a>"},{"name":"Сайт","value":"<a href=\"http://\" target=\"_blank\"></a>"}]}