{"id":"00399","locations":[{"status":"<div class=\"status ok\" title=\"Действующий\"></div>","address":"Краснодарский край, Мостовский р-н, п Мостовской, ул Южная, № 11","capacity":"32","type":["L","M1","M2","M3","N1","N2","N3","O1","O2","O3","O4"],"coords":["44.409212","40.774252"]},{"status":"<div class=\"status ok\" title=\"Действующий\"></div>","address":"Краснодарский край, г Лабинск, п Сахарного завода","capacity":"32","type":["L","M1","M2","M3","N1","N2","N3","O1","O2","O3","O4"]}],"company":[{"name":"Статус","value":"Аттестат действителен"},{"name":"Директор","value":"Ермак Сергей Пантелеевич"},{"name":"Полное наименование","value":"Общество с ограниченной ответственностью \"Лабинск-автотехсервис\""},{"name":"ОГРН","value":"1102314000227"},{"name":"Орг. форма","value":"Юридическое лицо"},{"name":"Адрес","value":"352510, Краснодарский край, г Лабинск, п Сахарного завода"}],"contacts":[{"name":"Телефон","value":"8 (928) 664-0041"},{"name":"E-mail","value":"<a href=\"mailto:kdb-flabinsk@yandex.ru\">kdb-flabinsk@yandex.ru</a>"},{"name":"Сайт","value":"<a href=\"http://лабинскавтотехсервис.рф\" target=\"_blank\">лабинскавтотехсервис.рф</a>"}]}