{"id":"00461","locations":[{"status":"<div class=\"status ok\" title=\"Действующий\"></div>","address":"187403, Ленинградская обл, Волховский р-н, г Волхов, ул Маяковского, 10","capacity":"46","type":["L","M1","M2","M3","N1","N2","N3","O1","O2","O3","O4"],"coords":["59.906946","32.352331"]}],"company":[{"name":"Статус","value":"Аттестат действителен"},{"name":"Директор","value":"Дмитриев Павел Владимирович"},{"name":"Полное наименование","value":"Общество с ограниченной ответственностью \"Техосмотр\""},{"name":"ОГРН","value":"1044700531292"},{"name":"Орг. форма","value":"Юридическое лицо"},{"name":"Адрес","value":"187403, Ленинградская обл, Волховский р-н, г Волхов, ул Маяковского, 10"}],"contacts":[{"name":"Телефон","value":"8 (905) 206-7152"},{"name":"E-mail","value":"<a href=\"mailto:tehosmotr-volhov@yandex.ru\">tehosmotr-volhov@yandex.ru</a>"},{"name":"Сайт","value":"<a href=\"http://www.tovolhov.ru\" target=\"_blank\">www.tovolhov.ru</a>"}]}