{"id":"00607","locations":[{"status":"<div class=\"status ok\" title=\"Действующий\"></div>","address":"346513, Ростовская обл, г Шахты, пер Шишкина, д. 162","capacity":"32","type":["M1","M2","M3","N1","N2","N3","O1","O2","O3","O4"],"coords":["47.725381","40.225984"]}],"company":[{"name":"Статус","value":"Аттестат действителен"},{"name":"Директор","value":"Василенко Дмитрий Александрович"},{"name":"Полное наименование","value":"Общество с ограниченной ответственностью \"ТехноЦентр\""},{"name":"ОГРН","value":"1096182002399"},{"name":"Орг. форма","value":"Юридическое лицо"},{"name":"Адрес","value":"346513, Ростовская обл, г Шахты, пер Шишкина, д. 162, комн. 3 А"}],"contacts":[{"name":"Телефон","value":"8 (918) 553-6100"},{"name":"E-mail","value":"<a href=\"mailto:t-centr161@mail.ru\">t-centr161@mail.ru</a>"},{"name":"Сайт","value":"<a href=\"http://pto-rf.ru/00607\" target=\"_blank\">pto-rf.ru/00607</a>"}]}