{"id":"00613","locations":[{"status":"<div class=\"status ok\" title=\"Действующий\"></div>","address":"Смоленская обл, Починковский р-н, г Починок, ул Юбилейная, д. 1-б","capacity":"16","type":["L","M1","M2","M3","N1","N2","N3","O1","O2","O3","O4"],"coords":["54.410751","32.460506"]},{"status":"<div class=\"status ok\" title=\"Действующий\"></div>","address":"Смоленская обл, г Вязьма, ул 25-го Октября, 47","capacity":"32","type":["L","M1","M2","M3","N1","N2","N3","O1","O2","O3","O4"],"coords":["55.191860","34.306661"]},{"status":"<div class=\"status ok\" title=\"Действующий\"></div>","address":"Смоленская обл, Гагаринский р-н, г Гагарин, пер Пионерский, 5","capacity":"16","type":["M1","M2","M3","N1","N2","N3","O1","O2","O3","O4"],"coords":["55.558575","34.992183"]},{"status":"<div class=\"status ok\" title=\"Действующий\"></div>","address":"Смоленская обл, г Смоленск, Промышленный р-н, ул Шевченко, 77А","capacity":"48","type":["L","M1","M2","M3","N1","N2","N3","O1","O2","O3","O4"],"coords":["54.780927","32.080420"]}],"company":[{"name":"Статус","value":"Аттестат действителен"},{"name":"Директор","value":"Жустарёв Александр Сергеевич"},{"name":"Полное наименование","value":"ЗАО \"Корпорация \"Центрсервис\""},{"name":"ОГРН","value":"1026701430535"},{"name":"Орг. форма","value":"Юридическое лицо"},{"name":"Адрес","value":"214020, Смоленская обл, г Смоленск, ул Шевченко, 77А"}],"contacts":[{"name":"Телефон","value":"8 (481) 231-1035"},{"name":"E-mail","value":"<a href=\"mailto:kcs67@mail.ru\">kcs67@mail.ru</a>"},{"name":"Сайт","value":"<a href=\"http://tehosmotr67.ru\" target=\"_blank\">tehosmotr67.ru</a>"}]}