{"id":"00873","locations":[{"status":"<div class=\"status ok\" title=\"Действующий\"></div>","address":"Новосибирская обл, Купинский р-н, г Купино, ул Южная, д 50а","capacity":"32","type":["L","M1","M2","M3","N1","N2","N3","O1","O2","O3","O4"],"coords":["54.364734","77.330321"]}],"company":[{"name":"Статус","value":"Аттестат действителен"},{"name":"Директор","value":"Кузнецов Виктор Васильевич"},{"name":"Полное наименование","value":"Общество с ограниченной ответственностью Пункт Технического Осмотра \"Кулунда\""},{"name":"ОГРН","value":"1055404162110"},{"name":"Орг. форма","value":"Юридическое лицо"},{"name":"Адрес","value":"632735, Новосибирская обл, Купинский р-н, г Купино, ул Южная, 50-а"}],"contacts":[{"name":"Телефон","value":"8 (383) 582-8055"},{"name":"E-mail","value":"<a href=\"mailto:pto16@mail.ru\">pto16@mail.ru</a>"},{"name":"Сайт","value":"<a href=\"http://\" target=\"_blank\"></a>"}]}