{"id":"01043","locations":[{"status":"<div class=\"status ok\" title=\"Действующий\"></div>","address":"359050, Калмыкия Респ, Городовиковский р-н, г Городовиковск, ул Буденного, 62 \"б\"","capacity":"16","type":["L","M1","M2","M3","N1","N2","N3"],"coords":["46.087161","41.921338"]}],"company":[{"name":"Статус","value":"Аттестат действителен"},{"name":"Директор","value":"Кулешов Алексей Петрович"},{"name":"Полное наименование","value":"ИП Кулешов А. П."},{"name":"ОГРН","value":"304080119100041"},{"name":"Орг. форма","value":"Индивидуальный предприниматель"},{"name":"Адрес","value":"359050, Республика Калмыкия, Городовиковский р-н., Городовиковск г."}],"contacts":[{"name":"Телефон","value":"8 (473) 192-142"},{"name":"E-mail","value":"<a href=\"mailto:ptod.gk@gmail.com\">ptod.gk@gmail.com</a>"},{"name":"Сайт","value":"<a href=\"http://Pto.gk@gmail.com\" target=\"_blank\">Pto.gk@gmail.com</a>"}]}