{"id":"01748","locations":[{"status":"<div class=\"status ok\" title=\"Действующий\"></div>","address":"607611, Нижегородская обл, Богородский р-н, с Доскино, ул Магистральная, д 44а","capacity":"16","type":["M1","N1","N2","N3"],"coords":["56.168150","43.736330"]}],"company":[{"name":"Статус","value":"Аттестат действителен"},{"name":"Директор","value":"Сальников Александр Васильевич"},{"name":"Полное наименование","value":"Общество с ограниченной ответственностью \"Проект\""},{"name":"ОГРН","value":"1025201453507"},{"name":"Орг. форма","value":"Юридическое лицо"},{"name":"Адрес","value":"607612, Нижегородская обл, Богородский р-н, п Буревестник, ул Центральная, д.60, кв.6"}],"contacts":[{"name":"Телефон","value":"8 (317) 048-096"},{"name":"E-mail","value":"<a href=\"mailto:proekt60@yandex.ru\">proekt60@yandex.ru</a>"},{"name":"Сайт","value":"<a href=\"http://machine-maintenance-388.buziness.site\" target=\"_blank\">machine-maintenance-388.buziness.site</a>"}]}