{"id":"01875","locations":[{"status":"<div class=\"status ok\" title=\"Действующий\"></div>","address":"Воронежская обл, Ольховатский р-н, п Заболотовка, ул Новаторов, 14 к","capacity":"32","type":["L","M1","M2","M3","N1","N2","N3","O1","O2","O3","O4"],"coords":["50.278121","39.318802"]}],"company":[{"name":"Статус","value":"Аттестат действителен"},{"name":"Директор","value":"Шинкаренко Андрей Юрьевич"},{"name":"Полное наименование","value":"Общество с ограниченной ответственностью \"Фаворит\""},{"name":"ОГРН","value":"1053664534769"},{"name":"Орг. форма","value":"Юридическое лицо"},{"name":"Адрес","value":"396691, Воронежская обл, Ольховатский р-н, п Заболотовка, ул Новаторов, 14 к"}],"contacts":[{"name":"Телефон","value":"8 (473) 953-1595"},{"name":"E-mail","value":"<a href=\"mailto:pto-favorit@yandex.ru\">pto-favorit@yandex.ru</a>"},{"name":"Сайт","value":"<a href=\"http://pto-favorit.ru/\" target=\"_blank\">pto-favorit.ru/</a>"}]}