{"id":"01988","locations":[{"status":"<div class=\"status ok\" title=\"Действующий\"></div>","address":"Тверская обл, г Кимры, ул 50 лет ВЛКСМ, 106","capacity":"32","type":["L","M1","M2","M3","N1","N2","N3","O1","O2","O3","O4"],"coords":["56.879009","37.388753"]}],"company":[{"name":"Статус","value":"Аттестат действителен"},{"name":"Директор","value":"Лебедев Сергей Леонидович"},{"name":"Полное наименование","value":"Общество с ограниченной ответственностью \"Универсал Плюс\""},{"name":"ОГРН","value":"1026901659784"},{"name":"Орг. форма","value":"Юридическое лицо"},{"name":"Адрес","value":"171506, Тверская обл, г Кимры, ул Карла Либкнехта, 26"}],"contacts":[{"name":"Телефон","value":"8 (482) 362-2677"},{"name":"E-mail","value":"<a href=\"mailto:uplus69@mail.ru\">uplus69@mail.ru</a>"},{"name":"Сайт","value":"<a href=\"http://pto-rf.ru/01988\" target=\"_blank\">pto-rf.ru/01988</a>"}]}