{"id":"02189","locations":[{"status":"<div class=\"status ok\" title=\"Действующий\"></div>","address":"197342, г Санкт-Петербург, ул Белоостровская, д. 19, лит. Е","capacity":"32","type":["M1","M2","M3","N1","N2","N3"],"coords":["59.988518","30.318815"]}],"company":[{"name":"Статус","value":"Аттестат действителен"},{"name":"Директор","value":"Салтанов Анатолий Васильевич"},{"name":"Полное наименование","value":"Общество с ограниченной ответственностью \"Станция диагностики \"Приморская\""},{"name":"ОГРН","value":"1027807567303"},{"name":"Орг. форма","value":"Юридическое лицо"},{"name":"Адрес","value":"197342, г Санкт-Петербург, ул Белоостровская, 19"}],"contacts":[{"name":"Телефон","value":"8 (124) 961-958"},{"name":"E-mail","value":"<a href=\"mailto:zemledelcheskaya@yandex.ru\">zemledelcheskaya@yandex.ru</a>"},{"name":"Сайт","value":"<a href=\"http://akp-spb.ru\" target=\"_blank\">akp-spb.ru</a>"}]}