{"id":"02486","locations":[{"status":"<div class=\"status ok\" title=\"Действующий\"></div>","address":"Красноярский край, г Лесосибирск, ул Промышленная, 76, зд. 5","capacity":"32","type":["M1","M2","M3","N1","N2","N3","O1","O2","O3","O4"],"coords":["58.306599","92.387244"]}],"company":[{"name":"Статус","value":"Аттестат действителен"},{"name":"Директор","value":"Димухаметов Олег Галимжанович"},{"name":"Полное наименование","value":"Общество с ограниченной ответственностью \"Лесосибирское АТП\""},{"name":"ОГРН","value":"1062454001224"},{"name":"Орг. форма","value":"Юридическое лицо"},{"name":"Адрес","value":"662548, Красноярский край, г Лесосибирск, ул Промышленная, д 76"}],"contacts":[{"name":"Телефон","value":"8 (913) 519-4555"},{"name":"E-mail","value":"<a href=\"mailto:lesosibATP@krasmail.ru\">lesosibATP@krasmail.ru</a>"},{"name":"Сайт","value":"<a href=\"http://нет\" target=\"_blank\">нет</a>"}]}