{"id":"02565","locations":[{"status":"<div class=\"status ok\" title=\"Действующий\"></div>","address":"367780, Дагестан Респ, Магарамкентский р-н, с Магарамкент","capacity":"16","type":["M1","M2","M3","N1","N2","O1","O2","O3","O4"],"coords":["41.617520","48.348245"]}],"company":[{"name":"Статус","value":"Аттестат действителен"},{"name":"Директор","value":"Эседуллаев Шарвели Юзбекович"},{"name":"Полное наименование","value":"Индивидуальный предприниматель Эседуллаев Шарвели Юзбекович"},{"name":"ОГРН","value":"310052323700038"},{"name":"Орг. форма","value":"Индивидуальный предприниматель"},{"name":"Адрес","value":"367780, Республика Дагестан, Магарамкентский р-н., с Магарамкент, Магарамкент с."}],"contacts":[{"name":"Телефон","value":"7 (928) 577-7059"},{"name":"E-mail","value":"<a href=\"mailto:sto059@mail.ru\">sto059@mail.ru</a>"},{"name":"Сайт","value":"<a href=\"http://tehosmotr-sharveli.ru\" target=\"_blank\">tehosmotr-sharveli.ru</a>"}]}