{"id":"05406","locations":[{"status":"<div class=\"status pause\" title=\"Приостановлен\"></div>","address":"445009, Самарская обл, г Тольятти, ул Новопромышленная, 14","capacity":"3","type":["M1"],"coords":["53.530905","49.436446"]}],"company":[{"name":"Статус","value":"Аттестат приостановлен"},{"name":"Директор","value":"Сорокин Владимир Юрьевич"},{"name":"Полное наименование","value":"Общество с ограниченной отвественностью \"Аллегра-авто\""},{"name":"ОГРН","value":"1096320007574"},{"name":"Орг. форма","value":"Юридическое лицо"},{"name":"Адрес","value":"445009, Самарская обл, г Тольятти, ул Новопромышленная, д. 14"}],"contacts":[{"name":"Телефон","value":"8 (848) 269-4395"},{"name":"E-mail","value":"<a href=\"mailto:allegra-avto@mail.ru\">allegra-avto@mail.ru</a>"},{"name":"Сайт","value":"<a href=\"http://\" target=\"_blank\"></a>"}]}