{"id":"05437","locations":[{"status":"<div class=\"status ok\" title=\"Действующий\"></div>","address":"630040 Новосибирская обл., Новосибирский р-н., Мочищенский сельсовет, Озерный п., Промышленная ул., д.6., к.8","capacity":"48","type":["L","M1","M2","M3","N1","N2","N3","O1","O2","O3","O4"],"coords":["55.131455","82.894307"]}],"company":[{"name":"Статус","value":"Аттестат действителен"},{"name":"Директор","value":"Рябошапко Дмитрий Иванович"},{"name":"Полное наименование","value":"Общество с ограниченной ответственностью \"НовоСтарт\""},{"name":"ОГРН","value":"1115476129878"},{"name":"Орг. форма","value":"Юридическое лицо"},{"name":"Адрес","value":"630534, Новосибирская обл, Новосибирский р-н, дп Мочище, ул Шоссейная, д 21"}],"contacts":[{"name":"Телефон","value":"7 (913) 377-9838"},{"name":"E-mail","value":"<a href=\"mailto:novostart54@mail.ru\">novostart54@mail.ru</a>"},{"name":"Сайт","value":"<a href=\"http://05437.umax.ru\" target=\"_blank\">05437.umax.ru</a>"}]}