{"id":"05467","locations":[{"status":"<div class=\"status pause\" title=\"Приостановлен\"></div>","address":"666671, Иркутская обл, г Усть-Илимск, ш Братское, д.23","capacity":"10","type":["M1","N1"],"coords":["57.986378","102.643283"]}],"company":[{"name":"Статус","value":"Аттестат приостановлен"},{"name":"Директор","value":"Шилимов Алексей Борисович"},{"name":"Полное наименование","value":"Общество с ограниченной ответственностью \"Усть-Илимск-АВТОВАЗ\""},{"name":"ОГРН","value":"1033802013629"},{"name":"Орг. форма","value":"Юридическое лицо"},{"name":"Адрес","value":"666671, Иркутская обл, г Усть-Илимск, ш Братское, д.23"}],"contacts":[{"name":"Телефон","value":"8 (395) 357-5656"},{"name":"E-mail","value":"<a href=\"mailto:ilimavtovaz@mail.ru\">ilimavtovaz@mail.ru</a>"},{"name":"Сайт","value":"<a href=\"http://\" target=\"_blank\"></a>"}]}