{"id":"05463","locations":[{"status":"<div class=\"status ok\" title=\"Действующий\"></div>","address":"346474, Ростовская обл, Октябрьский р-н, п Красногорняцкий, ул Центральная, 19","capacity":"16","type":["M1","M2","M3","N1","N2","N3","O1","O2","O3","O4"],"coords":["47.652904","40.191749"]}],"company":[{"name":"Статус","value":"Аттестат действителен"},{"name":"Директор","value":"Ершов Иван Александрович"},{"name":"Полное наименование","value":"Общество с ограниченной ответственностью \"Донтранссервис\""},{"name":"ОГРН","value":"1086150001233"},{"name":"Орг. форма","value":"Юридическое лицо"},{"name":"Адрес","value":"346400, Ростовская обл, г Новочеркасск, ул Щорса, д 99, оф 5"}],"contacts":[{"name":"Телефон","value":"8 (928) 153-3361"},{"name":"E-mail","value":"<a href=\"mailto:ivan-ershov@mail.ru\">ivan-ershov@mail.ru</a>"},{"name":"Сайт","value":"<a href=\"http://dontransto.wixsite.com/index\" target=\"_blank\">dontransto.wixsite.com/index</a>"}]}