{"id":"05753","locations":[{"status":"<div class=\"status pause\" title=\"Приостановлен\"></div>","address":"171750, Тверская обл, Сандовский р-н, пгт Сандово, ул Заречная, д.22","capacity":"4","type":["M1","N1"],"coords":["58.455819","36.420558"]}],"company":[{"name":"Статус","value":"Аттестат приостановлен"},{"name":"Директор","value":"Воробьева Ирина Анатольевна"},{"name":"Полное наименование","value":"Автономная некомерческая организация профессионального образования \"Автоманевр\""},{"name":"ОГРН","value":"1076900005126"},{"name":"Орг. форма","value":"Юридическое лицо"},{"name":"Адрес","value":"171750, Тверская обл, Сандовский р-н, пгт Сандово, ул Заречная, д.22"}],"contacts":[{"name":"Телефон","value":"7 (915) 730-8088"},{"name":"E-mail","value":"<a href=\"mailto:avtomanevr69@yandex.ru\">avtomanevr69@yandex.ru</a>"},{"name":"Сайт","value":"<a href=\"http://\" target=\"_blank\"></a>"}]}