{"id":"06057","locations":[{"status":"<div class=\"status ok\" title=\"Действующий\"></div>","address":"357500, Ставропольский край, г Пятигорск, ул Делегатская, д.97","capacity":"32","type":["M1","M2","N1"],"coords":["44.044351","42.999640"]}],"company":[{"name":"Статус","value":"Аттестат действителен"},{"name":"Директор","value":"Ангилов Александр Савельевич"},{"name":"Полное наименование","value":"Общество с ограниченной ответственностью \"СТО-ТСС Кавказ\""},{"name":"ОГРН","value":"1082632006005"},{"name":"Орг. форма","value":"Юридическое лицо"},{"name":"Адрес","value":"357500, Ставропольский край, г Пятигорск, ул Делегатская, д.97"}],"contacts":[{"name":"Телефон","value":"8 (905) 440-7525"},{"name":"E-mail","value":"<a href=\"mailto:stotsskavkaz@gmail.com\">stotsskavkaz@gmail.com</a>"},{"name":"Сайт","value":"<a href=\"http://tsskavkaz.lada.ru/ds/pages.php?id=178767&amp;rod_id=1832567\" target=\"_blank\">tsskavkaz.lada.ru/ds/pages.php?id=178767&amp;rod_id=1832567</a>"}]}