{"id":"06174","locations":[{"status":"<div class=\"status pause\" title=\"Приостановлен\"></div>","address":"Мурманская обл, г Мурманск, пр-кт Кирова, 51","capacity":"11","type":["M1","N1"],"coords":["68.950195","33.095983"]}],"company":[{"name":"Статус","value":"Аттестат приостановлен"},{"name":"Директор","value":"Рекечина Владислав Валентинович"},{"name":"Полное наименование","value":"Общество с ограниченной ответственностью \"Мурманск техосмотр\""},{"name":"ОГРН","value":"1115190027721"},{"name":"Орг. форма","value":"Юридическое лицо"},{"name":"Адрес","value":"183038, Мурманская обл, г Мурманск, ул Карла Либкнехта, д.27"}],"contacts":[{"name":"Телефон","value":"8 (815) 299-4411"},{"name":"E-mail","value":"<a href=\"mailto:tech51@ya.ru\">tech51@ya.ru</a>"},{"name":"Сайт","value":"<a href=\"http://\" target=\"_blank\"></a>"}]}