{"id":"06394","locations":[{"status":"<div class=\"status ok\" title=\"Действующий\"></div>","address":"Ставропольский край, Александровский р-н, с Александровское, ул Элеваторная, 18","capacity":"16","type":["M1","M2","M3","N1","N2","N3","O1","O2","O3","O4"],"coords":["44.725775","43.023319"]}],"company":[{"name":"Статус","value":"Аттестат действителен"},{"name":"Директор","value":"Савченко Александр Владимирович"},{"name":"Полное наименование","value":"ИП Савченко А. В."},{"name":"ОГРН","value":"310264902200024"},{"name":"Орг. форма","value":"Индивидуальный предприниматель"},{"name":"Адрес","value":"356304, Ставропольский край, Александровский р-н., с Александровское, Александровское с."}],"contacts":[{"name":"Телефон","value":"8 (865) 572-7340"},{"name":"E-mail","value":"<a href=\"mailto:savchenko_azs@mail.ru\">savchenko_azs@mail.ru</a>"},{"name":"Сайт","value":"<a href=\"http://pto-rf.ru/06394\" target=\"_blank\">pto-rf.ru/06394</a>"}]}