{"id":"06617","locations":[{"status":"<div class=\"status ok\" title=\"Действующий\"></div>","address":"Ленинградская обл, г Тосно, ш. Московское, д.2","capacity":"24","type":["M1","M2","M3","N1","N2","N3","O1","O2","O3","O4"],"coords":["59.567079","30.835013"]}],"company":[{"name":"Статус","value":"Аттестат действителен"},{"name":"Директор","value":"Саитов Фанил Мансурович"},{"name":"Полное наименование","value":"Общество с ограниченной ответственностью \"АвтоТахограф\""},{"name":"ОГРН","value":"1124716000925"},{"name":"Орг. форма","value":"Юридическое лицо"},{"name":"Адрес","value":"187000, Ленинградская обл, Тосненский р-н, г Тосно, ш Московское, д 2"}],"contacts":[{"name":"Телефон","value":"8 (911) 229-0326"},{"name":"E-mail","value":"<a href=\"mailto:avtotahograf@mail.ru\">avtotahograf@mail.ru</a>"},{"name":"Сайт","value":"<a href=\"http://06617.osmotr.to/\" target=\"_blank\">06617.osmotr.to/</a>"}]}