{"id":"06633","locations":[{"status":"<div class=\"status ok\" title=\"Действующий\"></div>","address":"685000, Магаданская обл, г Магадан, пер Марчеканский","capacity":"32","type":["M1","N1"],"coords":["59.546630","150.805819"]}],"company":[{"name":"Статус","value":"Аттестат действителен"},{"name":"Директор","value":"Хачиров Звяди Адинозович"},{"name":"Полное наименование","value":"Индивидуальный предприниматель Хачиров Звяди Адинозович"},{"name":"ОГРН","value":"306491034200011"},{"name":"Орг. форма","value":"Индивидуальный предприниматель"},{"name":"Адрес","value":"685000, Магаданская область, Магадан г."}],"contacts":[{"name":"Телефон","value":"8 (914) 868-4030"},{"name":"E-mail","value":"<a href=\"mailto:osminog49@mail.ru\">osminog49@mail.ru</a>"},{"name":"Сайт","value":"<a href=\"http://www.autocomp-osminog.ru\" target=\"_blank\">www.autocomp-osminog.ru</a>"}]}