{"id":"06716","locations":[{"status":"<div class=\"status ok\" title=\"Действующий\"></div>","address":"Омская обл, г Омск, ул Челюскинцев 4-я, д. 1","capacity":"24","type":["M1","N1"],"coords":["55.010189","73.418266"]}],"company":[{"name":"Статус","value":"Аттестат действителен"},{"name":"Директор","value":"Руденко Сергей Александрович"},{"name":"Полное наименование","value":"Индивидуальный предприниматель Руденко Сергей Александрович"},{"name":"ОГРН","value":"313554307900146"},{"name":"Орг. форма","value":"Индивидуальный предприниматель"},{"name":"Адрес","value":"644540, Омская область, Омский р-н., с. Пушкино"}],"contacts":[{"name":"Телефон","value":"8 (961) 884-9005"},{"name":"E-mail","value":"<a href=\"mailto:Rudenko_SA@mail.ru\">Rudenko_SA@mail.ru</a>"},{"name":"Сайт","value":"<a href=\"http://06716.umax.ru\" target=\"_blank\">06716.umax.ru</a>"}]}