{"id":"06776","locations":[{"status":"<div class=\"status ok\" title=\"Действующий\"></div>","address":"426000, Удмуртская Респ, г Ижевск, ул Карла Маркса, 55а","capacity":"22","type":["M1"],"coords":["56.829660","53.206082"]}],"company":[{"name":"Статус","value":"Аттестат действителен"},{"name":"Директор","value":"Ибрагимов Рафаэль Гаптыльахатович"},{"name":"Полное наименование","value":"Общество с ограниченной ответственностью \"Гарант-Моторс\""},{"name":"ОГРН","value":"1091841004188"},{"name":"Орг. форма","value":"Юридическое лицо"},{"name":"Адрес","value":"426000, Удмуртская Респ, г Ижевск, ул Карла Маркса, д. 55 а"}],"contacts":[{"name":"Телефон","value":"3 (412) 908-989"},{"name":"E-mail","value":"<a href=\"mailto:priemnaya@gms18.ru\">priemnaya@gms18.ru</a>"},{"name":"Сайт","value":"<a href=\"http://www.garant-mitsubishi.ru\" target=\"_blank\">www.garant-mitsubishi.ru</a>"}]}