{"id":"06835","locations":[{"status":"<div class=\"status pause\" title=\"Приостановлен\"></div>","address":"628404 Ханты-Мансийский Автономный округ - Югра АО., Сургут г., Нефтеюганское ш., д.23., кв.Станция технического обслуживания легковых автомобилей","capacity":"2","type":["M1","N1"]}],"company":[{"name":"Статус","value":"Аттестат приостановлен"},{"name":"Директор","value":"Исмагилов Денис Раильевич"},{"name":"Полное наименование","value":"ИП Исмагилов Д. Р."},{"name":"ОГРН","value":"313860208800030"},{"name":"Орг. форма","value":"Индивидуальный предприниматель"},{"name":"Адрес","value":"628408, Сургут г."}],"contacts":[{"name":"Телефон","value":"8 (982) 413-2111"},{"name":"E-mail","value":"<a href=\"mailto:ismagilov_denis@mail.ru\">ismagilov_denis@mail.ru</a>"},{"name":"Сайт","value":"<a href=\"http://\" target=\"_blank\"></a>"}]}