{"id":"06875","locations":[{"status":"<div class=\"status ok\" title=\"Действующий\"></div>","address":"Алтайский край, Волчихинский р-н, с Волчиха, ул Ленина, д. 388а","capacity":"32","type":["L","M1","M2","M3","N1","N2","N3","O1","O2","O3","O4"],"coords":["52.002620","80.342642"]}],"company":[{"name":"Статус","value":"Аттестат действителен"},{"name":"Директор","value":"Попов Николай Иванович"},{"name":"Полное наименование","value":"Общество с ограниченной ответственностью \"Школа Автомобилистов\""},{"name":"ОГРН","value":"1092235000208"},{"name":"Орг. форма","value":"Юридическое лицо"},{"name":"Адрес","value":"658930, Алтайский край, Волчихинский р-н, с Волчиха, ул Кирова, д 60, кв 2"}],"contacts":[{"name":"Телефон","value":"8 (385) 652-3330"},{"name":"E-mail","value":"<a href=\"mailto:spas-vrota@yandex.ru\">spas-vrota@yandex.ru</a>"},{"name":"Сайт","value":"<a href=\"http://www.avtovolchiha.ucoz.ru\" target=\"_blank\">www.avtovolchiha.ucoz.ru</a>"}]}