{"id":"06962","locations":[{"status":"<div class=\"status pause\" title=\"Приостановлен\"></div>","address":"Рязанская обл, г Ряжск, ул Новоряжская, д 35","capacity":"0","type":["M1","N1"],"coords":["53.707728","40.128175"]}],"company":[{"name":"Статус","value":"Аттестат приостановлен"},{"name":"Директор","value":"Оводова Нина Егоровна"},{"name":"Полное наименование","value":"Общество с ограниченной ответственностью \"Дежа-Вю\""},{"name":"ОГРН","value":"1116214000594"},{"name":"Орг. форма","value":"Юридическое лицо"},{"name":"Адрес","value":"391964, Рязанская обл, г Ряжск, ул Новоряжская, д.35"}],"contacts":[{"name":"Телефон","value":"8 (916) 172-5769"},{"name":"E-mail","value":"<a href=\"mailto:vic-and700@yandex.ru\">vic-and700@yandex.ru</a>"},{"name":"Сайт","value":"<a href=\"http://\" target=\"_blank\"></a>"}]}