{"id":"07012","locations":[{"status":"<div class=\"status ok\" title=\"Действующий\"></div>","address":"Алтайский край, г Бийск, ул Ленина, д. 228, Н-92","capacity":"16","type":["M1","M2","M3","N1","N2","N3","O1","O2","O3","O4"],"coords":["52.548350","85.230358"]}],"company":[{"name":"Статус","value":"Аттестат действителен"},{"name":"Директор","value":"Бедарев Владимир Викторович"},{"name":"Полное наименование","value":"Общество с ограниченной ответственностью \"Специализированная фирма \"РусЭксперТ\""},{"name":"ОГРН","value":"1022202666837"},{"name":"Орг. форма","value":"Юридическое лицо"},{"name":"Адрес","value":"659300, Алтайский край, г Бийск, ул Ленина, дом 228, помещение Н-92"}],"contacts":[{"name":"Телефон","value":"7 (385) 455-5201"},{"name":"E-mail","value":"<a href=\"mailto:rosexpert22@mail.ru\">rosexpert22@mail.ru</a>"},{"name":"Сайт","value":"<a href=\"http://sfret.ru/service.html#pto-point\" target=\"_blank\">sfret.ru/service.html#pto-point</a>"}]}