{"id":"07793","locations":[{"status":"<div class=\"status ok\" title=\"Действующий\"></div>","address":"600032, Владимирская обл, МО г Владимир (городской округ), г Владимир, ул Добросельская, 219 б","capacity":"20","type":["M1","N1"],"coords":["56.174585","40.494804"]}],"company":[{"name":"Статус","value":"Аттестат действителен"},{"name":"Директор","value":"Шичков Алексей Вячеславович"},{"name":"Полное наименование","value":"Общество с ограниченной ответственностью \"Индевел Групп\""},{"name":"ОГРН","value":"1113327010862"},{"name":"Орг. форма","value":"Юридическое лицо"},{"name":"Адрес","value":"600032, Владимирская обл, г Владимир, ул Добросельская, д. 219-Б"}],"contacts":[{"name":"Телефон","value":"8 (930) 832-1577"},{"name":"E-mail","value":"<a href=\"mailto:tekhosmotr@ladaprogress.ru\">tekhosmotr@ladaprogress.ru</a>"},{"name":"Сайт","value":"<a href=\"http://avtograd-vladimir.ru/\" target=\"_blank\">avtograd-vladimir.ru/</a>"}]}