{"id":"07953","locations":[{"status":"<div class=\"status ok\" title=\"Действующий\"></div>","address":"Ставропольский край, г Ставрополь, пр-кт Кулакова, д. 18-д","capacity":"64","type":["M1","N1"],"coords":["45.068557","41.925587"]}],"company":[{"name":"Статус","value":"Аттестат действителен"},{"name":"Директор","value":"Лебедев Михаил Сергеевич"},{"name":"Полное наименование","value":"Общество с ограниченной ответственностью \"Эксперт\""},{"name":"ОГРН","value":"1152651023469"},{"name":"Орг. форма","value":"Юридическое лицо"},{"name":"Адрес","value":"355029, Ставропольский край, г Ставрополь, ул Ленина, д. 456/2, пом. 142"}],"contacts":[{"name":"Телефон","value":"8 (968) 267-9063"},{"name":"E-mail","value":"<a href=\"mailto:pto26@otoexpert.ru\">pto26@otoexpert.ru</a>"},{"name":"Сайт","value":"<a href=\"http://аварком.рф/tekh-osmotr/\" target=\"_blank\">аварком.рф/tekh-osmotr/</a>"}]}