{"id":"08079","locations":[{"status":"<div class=\"status ok\" title=\"Действующий\"></div>","address":"433034, Ульяновская обл, Инзенский р-н, г Инза, ул Шоссейная, д 92","capacity":"48","type":["M1","M2","M3","N1","N2","N3","O1","O2","O3","O4"],"coords":["53.876398","46.365007"]}],"company":[{"name":"Статус","value":"Аттестат действителен"},{"name":"Директор","value":"Коннов Сергей Александрович"},{"name":"Полное наименование","value":"Общество с ограниченной ответственностью \"Альянс\""},{"name":"ОГРН","value":"1137309000355"},{"name":"Орг. форма","value":"Юридическое лицо"},{"name":"Адрес","value":"433033, Ульяновская обл, Инзенский р-н, г Инза, ул Фрунзе, д. 18"}],"contacts":[{"name":"Телефон","value":"8 (842) 412-4901"},{"name":"E-mail","value":"<a href=\"mailto:atp-inza@yandex.ru\">atp-inza@yandex.ru</a>"},{"name":"Сайт","value":"<a href=\"http://ptoinza.ru\" target=\"_blank\">ptoinza.ru</a>"}]}