{"id":"08174","locations":[{"status":"<div class=\"status ok\" title=\"Действующий\"></div>","address":"г Санкт-Петербург, ш Аннинское (Горелово), участок 8 (напротив дома 26а)","capacity":"40","type":["L","M1","N1"],"coords":["59.781501","30.095700"]}],"company":[{"name":"Статус","value":"Аттестат действителен"},{"name":"Директор","value":"Хотяинцев Вадим Вадимович"},{"name":"Полное наименование","value":"Общество с ограниченной ответственностью \"Автогор\""},{"name":"ОГРН","value":"1167847098132"},{"name":"Орг. форма","value":"Юридическое лицо"},{"name":"Адрес","value":"198323, г Санкт-Петербург, ш Аннинское (Горелово), д. 16"}],"contacts":[{"name":"Телефон","value":"8 (921) 322-6088"},{"name":"E-mail","value":"<a href=\"mailto:avtogor.spb@mail.ru\">avtogor.spb@mail.ru</a>"},{"name":"Сайт","value":"<a href=\"http://gtocentr.ru\" target=\"_blank\">gtocentr.ru</a>"}]}