{"id":"08207","locations":[{"status":"<div class=\"status ok\" title=\"Действующий\"></div>","address":"Московская обл, Воскресенский р-н, г Воскресенск, ул Старая промплощадка, д 1А","capacity":"48","type":["L","M1","M2","M3","N1","N2","N3","O1","O2","O3","O4"],"coords":["55.345350","38.736990"]}],"company":[{"name":"Статус","value":"Аттестат действителен"},{"name":"Директор","value":"Варфоломеев Александр Сергеевич"},{"name":"Полное наименование","value":"Общество с ограниченной ответственностью \"СИРИУС\""},{"name":"ОГРН","value":"1095005000716"},{"name":"Орг. форма","value":"Юридическое лицо"},{"name":"Адрес","value":"140200, Московская обл, Воскресенский р-н, г Воскресенск, ул 2-я Заводская, д. 4"}],"contacts":[{"name":"Телефон","value":"8 (916) 605-9307"},{"name":"E-mail","value":"<a href=\"mailto:vos-pto@mail.ru\">vos-pto@mail.ru</a>"},{"name":"Сайт","value":"<a href=\"http://08207.umax.ru\" target=\"_blank\">08207.umax.ru</a>"}]}