{"id":"08755","locations":[{"status":"<div class=\"status ok\" title=\"Действующий\"></div>","address":"г Москва, ул Куликовская, д 5","capacity":"32","type":["M1"],"coords":["55.570212","37.564437"]}],"company":[{"name":"Статус","value":"Аттестат действителен"},{"name":"Директор","value":"Казаков Андрей Сергеевич"},{"name":"Полное наименование","value":"Общество с ограниченной ответственностью \"ТЕХТРАНС-СБ\""},{"name":"ОГРН","value":"1167746093305"},{"name":"Орг. форма","value":"Юридическое лицо"},{"name":"Адрес","value":"117628, г Москва, ул Куликовская, д. 5, пом. 11"}],"contacts":[{"name":"Телефон","value":"8 (999) 111-2239"},{"name":"E-mail","value":"<a href=\"mailto:techtranssb@gmail.com\">techtranssb@gmail.com</a>"},{"name":"Сайт","value":"<a href=\"http://08755.овнд.рф\" target=\"_blank\">08755.овнд.рф</a>"}]}