{"id":"08961","locations":[{"status":"<div class=\"status ok\" title=\"Действующий\"></div>","address":"425350, Марий Эл Респ, г Козьмодемьянск, ул Некрасова, 61а","capacity":"16","type":["M1","N1"],"coords":["56.337072","46.543494"]}],"company":[{"name":"Статус","value":"Аттестат действителен"},{"name":"Директор","value":"Оплев Александр Владиславович"},{"name":"Полное наименование","value":"Индивидуальный предприниматель Оплев Александр Владиславович"},{"name":"ОГРН","value":"315122300002349"},{"name":"Орг. форма","value":"Индивидуальный предприниматель"},{"name":"Адрес","value":"425312, Республика Марий Эл, Горномарийский р-н., д. Пернянгаши"}],"contacts":[{"name":"Телефон","value":"8 (961) 335-3533"},{"name":"E-mail","value":"<a href=\"mailto:Sanek_Oplev@mail.ru\">Sanek_Oplev@mail.ru</a>"},{"name":"Сайт","value":"<a href=\"http://avtotehcentr12.com\" target=\"_blank\">avtotehcentr12.com</a>"}]}