{"id":"09209","locations":[{"status":"<div class=\"status ok\" title=\"Действующий\"></div>","address":"Татарстан Респ, г Набережные Челны, Промышленно-коммунальная зона,район НТЦ ОАО \"КАМАЗ\"","capacity":"24","type":["M1"]}],"company":[{"name":"Статус","value":"Аттестат действителен"},{"name":"Директор","value":"Сайфетдинов Кияметдин Каняфович"},{"name":"Полное наименование","value":"Общество с ограниченной ответственностью \"КАМА-ТО\""},{"name":"ОГРН","value":"1181690011183"},{"name":"Орг. форма","value":"Юридическое лицо"},{"name":"Адрес","value":"423800, Татарстан Респ, г Набережные Челны, ул Машиностроительная, д. 79А, оф. 4"}],"contacts":[{"name":"Телефон","value":"7 (951) 068-0175"},{"name":"E-mail","value":"<a href=\"mailto:kamato116@mail.ru\">kamato116@mail.ru</a>"},{"name":"Сайт","value":"<a href=\"http://kama-to.ru/\" target=\"_blank\">kama-to.ru/</a>"}]}