{"id":"09228","locations":[{"status":"<div class=\"status ok\" title=\"Действующий\"></div>","address":"172530, Тверская обл, Бельский р-н, г Белый, ул Солнечная, д. 10","capacity":"16","type":["L","M1","M2","M3","N1","N2","N3","O1","O2","O3","O4"],"coords":["55.821214","32.925824"]}],"company":[{"name":"Статус","value":"Аттестат действителен"},{"name":"Директор","value":"Котов Алексей Валерьевич"},{"name":"Полное наименование","value":"ИП Котов А. В."},{"name":"ОГРН","value":"304691228500069"},{"name":"Орг. форма","value":"Индивидуальный предприниматель"},{"name":"Адрес","value":"172521, Тверская область, г. Нелидово"}],"contacts":[{"name":"Телефон","value":"8 (910) 849-3004"},{"name":"E-mail","value":"<a href=\"mailto:white-sto@mail.ru\">white-sto@mail.ru</a>"},{"name":"Сайт","value":"<a href=\"http://www.09228.овнд.рф/\" target=\"_blank\">www.09228.овнд.рф/</a>"}]}