{"id":"09260","locations":[{"status":"<div class=\"status ok\" title=\"Действующий\"></div>","address":"Орловская обл, Орловский муниципальный район, с/п Большекуликовское, п Куликовский, ул Совхозная, д 2а, строение 2","capacity":"19","type":["M1","M2","M3","N1","N2","N3","O1","O2","O3","O4"],"coords":["52.937331","36.137948"]}],"company":[{"name":"Статус","value":"Аттестат действителен"},{"name":"Директор","value":"Бушаков Дмитрий Александрович"},{"name":"Полное наименование","value":"Общество с ограниченной ответственностью \"Партнер Агро\""},{"name":"ОГРН","value":"1085742001950"},{"name":"Орг. форма","value":"Юридическое лицо"},{"name":"Адрес","value":"302004, Орловская обл, г Орёл, ул 5 Августа, д. 64А"}],"contacts":[{"name":"Телефон","value":"8 (910) 200-0000"},{"name":"E-mail","value":"<a href=\"mailto:info@partneragro.com\">info@partneragro.com</a>"},{"name":"Сайт","value":"<a href=\"http://www.partneragro.ru/tehosmotr\" target=\"_blank\">www.partneragro.ru/tehosmotr</a>"}]}