{"id":"09304","locations":[{"status":"<div class=\"status ok\" title=\"Действующий\"></div>","address":"Ямало-Ненецкий АО., Новый Уренгой г., Западная промзона,","capacity":"48","type":["L","M1","M2","M3","N1","N2","N3","O1","O2","O3","O4"],"coords":["66.101330","76.555632"]}],"company":[{"name":"Статус","value":"Аттестат действителен"},{"name":"Директор","value":"Барышева Юлия Константиновна"},{"name":"Полное наименование","value":"Индивидуальный предприниматель Барышева Юлия Константиновна"},{"name":"ОГРН","value":"317890100023514"},{"name":"Орг. форма","value":"Индивидуальный предприниматель"},{"name":"Адрес","value":"629300, Новый Уренгой г."}],"contacts":[{"name":"Телефон","value":"8 (902) 829-6688"},{"name":"E-mail","value":"<a href=\"mailto:nur.atp@mail.ru\">nur.atp@mail.ru</a>"},{"name":"Сайт","value":"<a href=\"http://ip-baryisheva.ru\" target=\"_blank\">ip-baryisheva.ru</a>"}]}