{"id":"09411","locations":[{"status":"<div class=\"status ok\" title=\"Действующий\"></div>","address":"Крым Респ, Первомайский р-н, пгт Первомайское, ул Октябрьская, д 116 б, пом 11","capacity":"16","type":["M1","N1"],"coords":["45.721723","33.848116"]}],"company":[{"name":"Статус","value":"Аттестат действителен"},{"name":"Директор","value":"Довгань Валерий Анатольевич"},{"name":"Полное наименование","value":"Общество с ограниченной ответственностью \"АТК\""},{"name":"ОГРН","value":"1189112031525"},{"name":"Орг. форма","value":"Юридическое лицо"},{"name":"Адрес","value":"297501, Крым Респ, Симферопольский р-н, пгт. Молодежное, ул. Московская, д. 28"}],"contacts":[{"name":"Телефон","value":"7 (978) 848-0123"},{"name":"E-mail","value":"<a href=\"mailto:oooatk_crimea@mail.ru\">oooatk_crimea@mail.ru</a>"},{"name":"Сайт","value":"<a href=\"http://simfertehosmotr.ru\" target=\"_blank\">simfertehosmotr.ru</a>"}]}