{"id":"09585","locations":[{"status":"<div class=\"status ok\" title=\"Действующий\"></div>","address":"432072, Ульяновская обл, г Ульяновск, пр-кт Антонова, 55","capacity":"16","type":["M1","N1"],"coords":["54.379939","48.620255"]}],"company":[{"name":"Статус","value":"Аттестат действителен"},{"name":"Директор","value":"Исайкин Алексей Александрович"},{"name":"Полное наименование","value":"ИП Исайкин А. А."},{"name":"ОГРН","value":"318732500043719"},{"name":"Орг. форма","value":"Индивидуальный предприниматель"},{"name":"Адрес","value":"432072, Ульяновская область, Ульяновск г."}],"contacts":[{"name":"Телефон","value":"8 (937) 279-6926"},{"name":"E-mail","value":"<a href=\"mailto:isaikin.aleksei@mail.ru\">isaikin.aleksei@mail.ru</a>"},{"name":"Сайт","value":"<a href=\"http://TEХОСМОТР73.РФ\" target=\"_blank\">TEХОСМОТР73.РФ</a>"}]}