{"id":"09689","locations":[{"status":"<div class=\"status ok\" title=\"Действующий\"></div>","address":"622008, Свердловская обл, г Нижний Тагил, ул Краснознаменная, стр. 134Б","capacity":"14","type":["L","M1","M2","M3","N1","N2","N3","O1","O2","O3","O4"],"coords":["57.946923","59.916489"]}],"company":[{"name":"Статус","value":"Аттестат действителен"},{"name":"Директор","value":"Черемных Алексей Васильевич"},{"name":"Полное наименование","value":"Общество с ограниченной ответственностью \"КПК Глобал\""},{"name":"ОГРН","value":"1106623006467"},{"name":"Орг. форма","value":"Юридическое лицо"},{"name":"Адрес","value":"622013, Свердловская обл, г Нижний Тагил, ул Октябрьской Революции, д. 3, кв. 1"}],"contacts":[{"name":"Телефон","value":"8 (904) 987-7332"},{"name":"E-mail","value":"<a href=\"mailto:global.texosmotr@yandex.ru\">global.texosmotr@yandex.ru</a>"},{"name":"Сайт","value":"<a href=\"http://global96.ru\" target=\"_blank\">global96.ru</a>"}]}