{"id":"09861","locations":[{"status":"<div class=\"status ok\" title=\"Действующий\"></div>","address":"385200, Адыгея Респ, г Адыгейск, ул Коммунистическая, д. 1А/5 и 1А/6","capacity":"32","type":["M1"],"coords":["44.874535","39.185932"]}],"company":[{"name":"Статус","value":"Аттестат действителен"},{"name":"Директор","value":"Гучетль Радик Асланович"},{"name":"Полное наименование","value":"Общество с ограниченной ответственностью \"ЮГ-СТО\""},{"name":"ОГРН","value":"1180105002637"},{"name":"Орг. форма","value":"Юридическое лицо"},{"name":"Адрес","value":"385200, Адыгея Респ, г Адыгейск, ул Коммунистическая, д. 1А/5"}],"contacts":[{"name":"Телефон","value":"8 (988) 477-8107"},{"name":"E-mail","value":"<a href=\"mailto:9181819911@mail.ru\">9181819911@mail.ru</a>"},{"name":"Сайт","value":"<a href=\"http://tehosmotr01.ru\" target=\"_blank\">tehosmotr01.ru</a>"}]}