{"id":"09919","locations":[{"status":"<div class=\"status ok\" title=\"Действующий\"></div>","address":"Московская обл, г Королев, проезд Канальный, д. 5","capacity":"32","type":["M1","N1"],"coords":["55.910205","37.841540"]}],"company":[{"name":"Статус","value":"Аттестат действителен"},{"name":"Директор","value":"Лукьянов Вадим Викторович"},{"name":"Полное наименование","value":"ИП Лукьянов В. В."},{"name":"ОГРН","value":"319502700033704"},{"name":"Орг. форма","value":"Индивидуальный предприниматель"},{"name":"Адрес","value":"140010, Московская область, Люберецкий р-н., г Люберцы"}],"contacts":[{"name":"Телефон","value":"8 (966) 001-8464"},{"name":"E-mail","value":"<a href=\"mailto:L0507777@mail.ru\">L0507777@mail.ru</a>"},{"name":"Сайт","value":"<a href=\"http://09919.umax.ru\" target=\"_blank\">09919.umax.ru</a>"}]}