{"id":"10121","locations":[{"status":"<div class=\"status pause\" title=\"Приостановлен\"></div>","address":"Тверская обл, Вышневолоцкий р-н, г Вышний Волочек, ул Ленинградская дамба, дом 3а","capacity":"0","type":["M1","N1"],"coords":["57.615806","34.477116"]}],"company":[{"name":"Статус","value":"Аттестат приостановлен"},{"name":"Директор","value":"Петров Евгений Владимирович"},{"name":"Полное наименование","value":"Общество с ограниченной ответственностью \"ЭКСПЕРТ-АВТО\""},{"name":"ОГРН","value":"1196952010166"},{"name":"Орг. форма","value":"Юридическое лицо"},{"name":"Адрес","value":"171121, Тверская обл, Вышневолоцкий р-н, пгт Красномайский, пер. Профсоюзный, д. 4"}],"contacts":[{"name":"Телефон","value":"8 (920) 167-1506"},{"name":"E-mail","value":"<a href=\"mailto:petrov2792@mail.ru\">petrov2792@mail.ru</a>"},{"name":"Сайт","value":"<a href=\"http://\" target=\"_blank\"></a>"}]}