{"id":"10334","locations":[{"status":"<div class=\"status ok\" title=\"Действующий\"></div>","address":"Еврейская Аобл, г Биробиджан, ул. Советская , д. 117б","capacity":"32","type":["M1","N1"],"coords":["48.770174","132.945838"]}],"company":[{"name":"Статус","value":"Аттестат действителен"},{"name":"Директор","value":"Буровников Юрий Васильевич"},{"name":"Полное наименование","value":"ИП Буровников Ю. В."},{"name":"ОГРН","value":"319790100005394"},{"name":"Орг. форма","value":"Индивидуальный предприниматель"},{"name":"Адрес","value":"679016, Еврейская автономная область, Биробиджан г."}],"contacts":[{"name":"Телефон","value":"8 (924) 646-9144"},{"name":"E-mail","value":"<a href=\"mailto:ecspert1964@bk.ru\">ecspert1964@bk.ru</a>"},{"name":"Сайт","value":"<a href=\"http://toeao.ru\" target=\"_blank\">toeao.ru</a>"}]}