{"id":"10383","locations":[{"status":"<div class=\"status ok\" title=\"Действующий\"></div>","address":"Челябинская обл, г Челябинск, ул Героев Танкограда, д. 61п","capacity":"32","type":["M1"],"coords":["55.209195","61.441792"]}],"company":[{"name":"Статус","value":"Аттестат действителен"},{"name":"Директор","value":"Равичев Юрий Викторович"},{"name":"Полное наименование","value":"Общество с ограниченной ответственностью \"РВЧ-Авто\""},{"name":"ОГРН","value":"1197456044895"},{"name":"Орг. форма","value":"Юридическое лицо"},{"name":"Адрес","value":"454090, Челябинская обл, г Челябинск, ул Свободы, д. 145, кв. 165"}],"contacts":[{"name":"Телефон","value":"8 (951) 777-1114"},{"name":"E-mail","value":"<a href=\"mailto:mashalove-95@mail.ru\">mashalove-95@mail.ru</a>"},{"name":"Сайт","value":"<a href=\"http://tehosmotr174.ru\" target=\"_blank\">tehosmotr174.ru</a>"}]}