{"id":"10492","locations":[{"status":"<div class=\"status pause\" title=\"Приостановлен\"></div>","address":"249210, Калужская обл, Бабынинский р-н, п Воротынск, ул Промышленная, д 11","capacity":"24","type":["M1","N1"],"coords":["54.476500","36.048180"]}],"company":[{"name":"Статус","value":"Аттестат приостановлен"},{"name":"Директор","value":"Перевозчикова Ксения Васильевна"},{"name":"Полное наименование","value":"Общество с ограниченной ответственностью \"Авто Импорт\""},{"name":"ОГРН","value":"1194027014037"},{"name":"Орг. форма","value":"Юридическое лицо"},{"name":"Адрес","value":"248021, Калужская обл, г Калуга, ул Московская, д. 231, оф. 57"}],"contacts":[{"name":"Телефон","value":"8 (915) 310-1193"},{"name":"E-mail","value":"<a href=\"mailto:avto-import89@mail.ru\">avto-import89@mail.ru</a>"},{"name":"Сайт","value":"<a href=\"http://pto-rf.ru/10492\" target=\"_blank\">pto-rf.ru/10492</a>"}]}