{"id":"10516","locations":[{"status":"<div class=\"status ok\" title=\"Действующий\"></div>","address":"Курганская обл, г Курган, ул Б.Петрова, 103, стр. 1","capacity":"48","type":["L","M1","M2","M3","N1","N2","N3","O1","O2","O3","O4"],"coords":["55.473500","65.336519"]}],"company":[{"name":"Статус","value":"Аттестат действителен"},{"name":"Директор","value":"Сычков Михаил Владимирович"},{"name":"Полное наименование","value":"Общество с ограниченной ответственностью \"Автобокс\""},{"name":"ОГРН","value":"1194501004477"},{"name":"Орг. форма","value":"Юридическое лицо"},{"name":"Адрес","value":"640023, Курганская обл, г Курган, ул. Майская (п.тер. Левашово), д. 2 А"}],"contacts":[{"name":"Телефон","value":"8 (912) 571-7120"},{"name":"E-mail","value":"<a href=\"mailto:avtobox45@bk.ru\">avtobox45@bk.ru</a>"},{"name":"Сайт","value":"<a href=\"http://10516.umax.ru\" target=\"_blank\">10516.umax.ru</a>"}]}