{"id":"10882","locations":[{"status":"<div class=\"status ok\" title=\"Действующий\"></div>","address":"Забайкальский край, Читинский р-н, с. Засопка, ул. Проезжая, уч. 6, строен. 1","capacity":"32","type":["L","M1","M2","M3","N1","N2","N3","O1","O2","O3","O4"],"coords":["52.013375","113.422339"]}],"company":[{"name":"Статус","value":"Аттестат действителен"},{"name":"Директор","value":"Дорожкова Анна Сергеевна"},{"name":"Полное наименование","value":"Индивидуальный предприниматель Дорожкова Анна Сергеевна"},{"name":"ОГРН","value":"304753434300305"},{"name":"Орг. форма","value":"Индивидуальный предприниматель"},{"name":"Адрес","value":"672012, Забайкальский край, Чита г."}],"contacts":[{"name":"Телефон","value":"8 (914) 529-1929"},{"name":"E-mail","value":"<a href=\"mailto:dorozhkova1981@mail.ru\">dorozhkova1981@mail.ru</a>"},{"name":"Сайт","value":"<a href=\"http://tehosmotr75.ru\" target=\"_blank\">tehosmotr75.ru</a>"}]}