{"id":"10892","locations":[{"status":"<div class=\"status ok\" title=\"Действующий\"></div>","address":"Московская обл, Дмитровский р-н, г/п Дмитров, с Борисово","capacity":"64","type":["L","M1","M2","M3","N1","N2","N3"],"coords":["56.322519","37.565021"]}],"company":[{"name":"Статус","value":"Аттестат действителен"},{"name":"Директор","value":"Архипов Андрей Сергеевич"},{"name":"Полное наименование","value":"Общество с ограниченной ответственностью \"ТЕХАВТОКОНТРОЛЬ\""},{"name":"ОГРН","value":"5167746395878"},{"name":"Орг. форма","value":"Юридическое лицо"},{"name":"Адрес","value":"129336 Москва г., Москва г., вн. тер. г. Муниципальный округ Лосиноостровский, ул. Стартовая, д.21., кв.94"}],"contacts":[{"name":"Телефон","value":"8 (985) 750-6863"},{"name":"E-mail","value":"<a href=\"mailto:texavtokontrol@gmail.com\">texavtokontrol@gmail.com</a>"},{"name":"Сайт","value":"<a href=\"http://Tekhavtokontrol.ru\" target=\"_blank\">Tekhavtokontrol.ru</a>"}]}