{"id":"11142","locations":[{"status":"<div class=\"status ok\" title=\"Действующий\"></div>","address":"Саратовская обл, г. Саратов, ул. Танкистов, д. 84А","capacity":"32","type":["L","M1","M2","M3","N1","N2","N3","O1","O2","O3","O4"],"coords":["51.573631","46.025732"]},{"status":"<div class=\"status ok\" title=\"Действующий\"></div>","address":"Саратовская обл, г.о. город Саратов, г. Саратов, ул. Аэропорт, зд. 24Б, стр. 1","capacity":"32","type":["L","M1","M2","M3","N1","N2","N3","O1","O2","O3","O4"],"coords":["51.557328","46.042557"]}],"company":[{"name":"Статус","value":"Аттестат действителен"},{"name":"Директор","value":"Николаева Екатерина Дмитриевна"},{"name":"Полное наименование","value":"Общество с ограниченной ответственностью \"ТРАНСЭКСПЕРТ САРАТОВ\""},{"name":"ОГРН","value":"1176451013947"},{"name":"Орг. форма","value":"Юридическое лицо"},{"name":"Адрес","value":"410052, Саратовская обл, г Саратов, ул Одесская, д. 20, оф. 220"}],"contacts":[{"name":"Телефон","value":"8 (845) 237-7300"},{"name":"E-mail","value":"<a href=\"mailto:expertiza064@gmail.com\">expertiza064@gmail.com</a>"},{"name":"Сайт","value":"<a href=\"http:// transexpert-saratov.wixsite.com/transexpert-saratov\" target=\"_blank\"> transexpert-saratov.wixsite.com/transexpert-saratov</a>"}]}